byted_overpass_tiktok_pack_poi/__init__.py
byted_overpass_tiktok_pack_poi-0.0.1.dist-info/METADATA
byted_overpass_tiktok_pack_poi-0.0.1.dist-info/WHEEL
byted_overpass_tiktok_pack_poi-0.0.1.dist-info/top_level.txt
byted_overpass_tiktok_pack_poi-0.0.1.dist-info/RECORD
